{
  "mcpServers": {
    "whimsical": {
      "type": "http",
      "url": "https://mcp.whimsical.com/mcp"
    },
    "supabase": {
      "type": "http",
      "url": "https://mcp.supabase.com/mcp"
    },
    "notion": {
      "type": "http",
      "url": "https://mcp.notion.com/mcp"
    },
    "windsor": {
      "type": "http",
      "url": "https://mcp.windsor.ai/"
    },
    "canva": {
      "type": "http",
      "url": "https://mcp.canva.com/mcp"
    },
    "runway": {
      "type": "http",
      "url": "https://mcp.runwayml.com/mcp"
    },
    "replicate": {
      "type": "sse",
      "url": "https://mcp.replicate.com/sse"
    },
    "apify": {
      "command": "npx",
      "args": ["-y", "@apify/actors-mcp-server"],
      "env": {
        "APIFY_TOKEN": "${APIFY_TOKEN}"
      }
    },
    "elevenlabs": {
      "command": "uvx",
      "args": ["elevenlabs-mcp"],
      "env": {
        "ELEVENLABS_API_KEY": "${ELEVENLABS_API_KEY}"
      }
    }
  }
}
